pdm_invoke/__init__.py
pdm_invoke/main.py
pdm_invoke-0.0.5.dist-info/entry_points.txt
pdm_invoke-0.0.5.dist-info/WHEEL
pdm_invoke-0.0.5.dist-info/METADATA
pdm_invoke-0.0.5.dist-info/licenses/LICENSE
pdm_invoke-0.0.5.dist-info/RECORD
