Metadata-Version: 2.1
Name: pdm-invoke
Version: 0.0.5
Summary: pdm shortcuts for invoke projects
License: MIT
Author-email: Abdul Hamid <abdulachik@icloud.com>
Requires-Python: >=3.7
Project-URL: homepage, https://github.com/sicksid/pdm-invoke
